pyannotators_acronyms/__init__.py
pyannotators_acronyms/acronyms.py
pyannotators_acronyms-0.5.243.dist-info/entry_points.txt
pyannotators_acronyms-0.5.243.dist-info/licenses/LICENSE
pyannotators_acronyms-0.5.243.dist-info/WHEEL
pyannotators_acronyms-0.5.243.dist-info/METADATA
pyannotators_acronyms-0.5.243.dist-info/RECORD
